{
	"name": "Event sheet 1",
	"events": [
		{
			"eventType": "comment",
			"text": "Variable for taps"
		},
		{
			"eventType": "variable",
			"name": "Currency",
			"type": "number",
			"initialValue": "0",
			"comment": "",
			"isStatic": false,
			"isConstant": false,
			"sid": 919272127781115
		},
		{
			"eventType": "variable",
			"name": "TapNumber",
			"type": "number",
			"initialValue": "1",
			"comment": "conteo de taps al ahcer click",
			"isStatic": false,
			"isConstant": false,
			"sid": 559119910107418
		},
		{
			"eventType": "variable",
			"name": "Multiplier",
			"type": "number",
			"initialValue": "1",
			"comment": "",
			"isStatic": false,
			"isConstant": false,
			"sid": 935290196678315
		},
		{
			"eventType": "variable",
			"name": "TouchPanID",
			"type": "number",
			"initialValue": "0",
			"comment": "",
			"isStatic": false,
			"isConstant": false,
			"sid": 948840492798627
		},
		{
			"eventType": "variable",
			"name": "TouchLastX",
			"type": "number",
			"initialValue": "0",
			"comment": "",
			"isStatic": false,
			"isConstant": false,
			"sid": 433540801412145
		},
		{
			"eventType": "comment",
			"text": "Variables for time"
		},
		{
			"eventType": "variable",
			"name": "UnixtimeDiff",
			"type": "number",
			"initialValue": "0",
			"comment": "",
			"isStatic": false,
			"isConstant": false,
			"sid": 191498679347229
		},
		{
			"eventType": "variable",
			"name": "SecondsPassed",
			"type": "number",
			"initialValue": "0",
			"comment": "",
			"isStatic": false,
			"isConstant": false,
			"sid": 745214651088806
		},
		{
			"eventType": "variable",
			"name": "UnixtimeClose",
			"type": "number",
			"initialValue": "0",
			"comment": "",
			"isStatic": false,
			"isConstant": false,
			"sid": 236963274458595
		},
		{
			"eventType": "variable",
			"name": "UnixtimeOpen",
			"type": "number",
			"initialValue": "0",
			"comment": "",
			"isStatic": false,
			"isConstant": false,
			"sid": 446144169395532
		},
		{
			"eventType": "comment",
			"text": "Variable for init"
		},
		{
			"eventType": "variable",
			"name": "FirstLoad",
			"type": "boolean",
			"initialValue": "false",
			"comment": "",
			"isStatic": false,
			"isConstant": false,
			"sid": 929174673920114
		},
		{
			"eventType": "comment",
			"text": "Variable for text"
		},
		{
			"eventType": "variable",
			"name": "LogMultiple",
			"type": "number",
			"initialValue": "0",
			"comment": "",
			"isStatic": false,
			"isConstant": false,
			"sid": 655090624839309
		},
		{
			"eventType": "comment",
			"text": "Variables for aspect"
		},
		{
			"eventType": "variable",
			"name": "OriginalHeight",
			"type": "number",
			"initialValue": "0",
			"comment": "",
			"isStatic": false,
			"isConstant": false,
			"sid": 175673185487877
		},
		{
			"eventType": "variable",
			"name": "OriginalWidth",
			"type": "number",
			"initialValue": "0",
			"comment": "",
			"isStatic": false,
			"isConstant": false,
			"sid": 374526522831793
		},
		{
			"eventType": "comment",
			"text": ""
		},
		{
			"eventType": "group",
			"disabled": false,
			"title": "Init",
			"description": "",
			"isActiveOnStart": true,
			"children": [
				{
					"eventType": "group",
					"disabled": false,
					"title": "Unixtime",
					"description": "",
					"isActiveOnStart": true,
					"children": [
						{
							"eventType": "block",
							"conditions": [
								{
									"id": "on-suspend",
									"objectClass": "System",
									"sid": 164647656318722
								}
							],
							"actions": [
								{
									"id": "set-eventvar-value",
									"objectClass": "System",
									"sid": 339997961121215,
									"parameters": {
										"variable": "UnixtimeClose",
										"value": "unixtime"
									}
								}
							],
							"sid": 843768885129222
						},
						{
							"eventType": "block",
							"conditions": [
								{
									"id": "on-resume",
									"objectClass": "System",
									"sid": 853356928513713
								}
							],
							"actions": [
								{
									"id": "set-eventvar-value",
									"objectClass": "System",
									"sid": 707680507727783,
									"parameters": {
										"variable": "UnixtimeOpen",
										"value": "unixtime"
									}
								},
								{
									"id": "set-eventvar-value",
									"objectClass": "System",
									"sid": 750302170373784,
									"parameters": {
										"variable": "UnixtimeDiff",
										"value": "UnixtimeOpen-UnixtimeClose"
									}
								},
								{
									"id": "set-eventvar-value",
									"objectClass": "System",
									"sid": 676537205724615,
									"parameters": {
										"variable": "SecondsPassed",
										"value": "ceil(UnixtimeDiff/1000)"
									}
								},
								{
									"id": "set-eventvar-value",
									"objectClass": "System",
									"sid": 268777312662782,
									"parameters": {
										"variable": "Currency",
										"value": "Currency +(Multiplier*SecondsPassed)"
									}
								},
								{
									"id": "set-visible",
									"objectClass": "CurrencyOffline",
									"sid": 230669139370831,
									"parameters": {
										"visibility": "visible"
									}
								},
								{
									"id": "set-text",
									"objectClass": "CurrencyOffline",
									"sid": 971491497597741,
									"parameters": {
										"text": "\"¡Ganaste \" & (Multiplier * SecondsPassed) & \" monedas mientras no estabas!\""
									}
								},
								{
									"id": "wait",
									"objectClass": "System",
									"sid": 424821530097311,
									"parameters": {
										"seconds": "2.0",
										"use-timescale": true
									}
								},
								{
									"id": "set-visible",
									"objectClass": "CurrencyOffline",
									"sid": 408924317254299,
									"parameters": {
										"visibility": "invisible"
									}
								}
							],
							"sid": 860504578037450
						}
					],
					"sid": 241719208250430
				},
				{
					"eventType": "block",
					"conditions": [
						{
							"id": "on-start-of-layout",
							"objectClass": "System",
							"sid": 479504950043829
						}
					],
					"actions": [
						{
							"id": "set-size",
							"objectClass": "NivelArray",
							"sid": 290770472668075,
							"parameters": {
								"width": "9",
								"height": "1",
								"depth": "1"
							}
						},
						{
							"id": "set-at-xyz",
							"objectClass": "NivelArray",
							"sid": 353310067614759,
							"parameters": {
								"x": "1",
								"y": "0",
								"z": "0",
								"value": "10"
							}
						},
						{
							"id": "set-at-xyz",
							"objectClass": "NivelArray",
							"sid": 679871972134905,
							"parameters": {
								"x": "2",
								"y": "0",
								"z": "0",
								"value": "30"
							}
						},
						{
							"id": "set-at-xyz",
							"objectClass": "NivelArray",
							"sid": 707108306253594,
							"parameters": {
								"x": "3",
								"y": "0",
								"z": "0",
								"value": "70"
							}
						},
						{
							"id": "set-at-xyz",
							"objectClass": "NivelArray",
							"sid": 728911852648439,
							"parameters": {
								"x": "4",
								"y": "0",
								"z": "0",
								"value": "150"
							}
						},
						{
							"id": "set-at-xyz",
							"objectClass": "NivelArray",
							"sid": 395148471158259,
							"parameters": {
								"x": "5",
								"y": "0",
								"z": "0",
								"value": "310"
							}
						},
						{
							"id": "set-at-xyz",
							"objectClass": "NivelArray",
							"sid": 236551218591375,
							"parameters": {
								"x": "6",
								"y": "0",
								"z": "0",
								"value": "630"
							}
						},
						{
							"id": "set-at-xyz",
							"objectClass": "NivelArray",
							"sid": 500699013743234,
							"parameters": {
								"x": "7",
								"y": "0",
								"z": "0",
								"value": "1270"
							}
						},
						{
							"id": "set-at-xyz",
							"objectClass": "NivelArray",
							"sid": 683892238227061,
							"parameters": {
								"x": "8",
								"y": "0",
								"z": "0",
								"value": "2550"
							}
						},
						{
							"id": "set-at-xyz",
							"objectClass": "NivelArray",
							"sid": 650274544308623,
							"parameters": {
								"x": "9",
								"y": "0",
								"z": "0",
								"value": "5110"
							}
						},
						{
							"id": "set-eventvar-value",
							"objectClass": "System",
							"sid": 593557986173219,
							"parameters": {
								"variable": "OriginalHeight",
								"value": "Character.Height"
							}
						},
						{
							"id": "set-eventvar-value",
							"objectClass": "System",
							"sid": 570275958414993,
							"parameters": {
								"variable": "OriginalWidth",
								"value": "Character.Width"
							}
						},
						{
							"id": "scroll-to-object",
							"objectClass": "System",
							"sid": 340572672249351,
							"parameters": {
								"object": "Character"
							}
						},
						{
							"id": "scroll-to-position",
							"objectClass": "System",
							"sid": 136750753843075,
							"parameters": {
								"x": "(LayoutWidth / 2)\r\n",
								"y": "(LayoutHeight / 2)"
							}
						},
						{
							"id": "play",
							"objectClass": "Audio",
							"sid": 533754405413611,
							"parameters": {
								"audio-file": "theme_A_nice_little_village",
								"loop": "not-looping",
								"volume": "-30",
								"stereo-pan": "0",
								"tag-optional": "\"mainTheme\""
							}
						}
					],
					"sid": 854185379082529,
					"children": [
						{
							"eventType": "block",
							"conditions": [
								{
									"id": "compare-boolean-eventvar",
									"objectClass": "System",
									"sid": 194374452450758,
									"parameters": {
										"variable": "FirstLoad"
									}
								}
							],
							"actions": [
								{
									"id": "set-boolean-eventvar",
									"objectClass": "System",
									"sid": 985250029232106,
									"parameters": {
										"variable": "FirstLoad",
										"value": "false"
									}
								}
							],
							"sid": 964661426581986
						},
						{
							"eventType": "block",
							"conditions": [
								{
									"id": "compare-boolean-eventvar",
									"objectClass": "System",
									"sid": 261754438189785,
									"parameters": {
										"variable": "FirstLoad"
									},
									"isInverted": true
								}
							],
							"actions": [
								{
									"id": "load",
									"objectClass": "System",
									"sid": 125149064539723,
									"parameters": {
										"slot": "\"mysave\""
									}
								},
								{
									"id": "load",
									"objectClass": "Dictionary",
									"sid": 434524627292072,
									"parameters": {
										"json": "AJAX.LastData"
									}
								}
							],
							"sid": 492004137487024
						}
					]
				},
				{
					"eventType": "block",
					"conditions": [
						{
							"id": "on-completed",
							"objectClass": "AJAX",
							"sid": 533700997051661,
							"disabled": true,
							"parameters": {
								"tag": "\"UnitLoad\""
							}
						}
					],
					"actions": [],
					"sid": 527835657269931
				},
				{
					"eventType": "block",
					"conditions": [
						{
							"id": "every-tick",
							"objectClass": "System",
							"sid": 919792816987042
						}
					],
					"actions": [
						{
							"id": "set-text",
							"objectClass": "LunaLevel",
							"sid": 847614809290302,
							"parameters": {
								"text": "\"Level \" &Character.Level"
							}
						}
					],
					"sid": 458984353660052
				},
				{
					"eventType": "block",
					"conditions": [
						{
							"id": "every-x-seconds",
							"objectClass": "System",
							"sid": 636782398688969,
							"parameters": {
								"interval-seconds": "10"
							}
						}
					],
					"actions": [
						{
							"id": "save",
							"objectClass": "System",
							"sid": 302812190293404,
							"parameters": {
								"slot": "\"mysave\""
							}
						}
					],
					"sid": 432031974609273
				}
			],
			"sid": 767527786130118
		},
		{
			"eventType": "group",
			"disabled": false,
			"title": "PassiveEarning",
			"description": "",
			"isActiveOnStart": true,
			"children": [
				{
					"eventType": "block",
					"conditions": [
						{
							"id": "on-object-clicked",
							"objectClass": "Mouse",
							"sid": 309774825750241,
							"parameters": {
								"mouse-button": "left",
								"click-type": "clicked",
								"object-clicked": "Character"
							}
						}
					],
					"actions": [
						{
							"id": "add-to-eventvar",
							"objectClass": "System",
							"sid": 474505176987618,
							"parameters": {
								"variable": "Currency",
								"value": "1*Multiplier"
							}
						}
					],
					"sid": 605295819855558,
					"disabled": true
				},
				{
					"eventType": "block",
					"conditions": [
						{
							"id": "every-x-seconds",
							"objectClass": "System",
							"sid": 766495939268105,
							"parameters": {
								"interval-seconds": "1.0"
							}
						}
					],
					"actions": [
						{
							"id": "add-to-eventvar",
							"objectClass": "System",
							"sid": 559402037266195,
							"parameters": {
								"variable": "Currency",
								"value": "TapNumber+Character.PassiveTapCount"
							}
						}
					],
					"sid": 772353414454222,
					"disabled": true
				}
			],
			"sid": 810506089196584
		},
		{
			"eventType": "group",
			"disabled": false,
			"title": "CharacterEarning",
			"description": "",
			"isActiveOnStart": true,
			"children": [
				{
					"eventType": "block",
					"conditions": [
						{
							"id": "on-object-clicked",
							"objectClass": "Mouse",
							"sid": 773210142554676,
							"parameters": {
								"mouse-button": "left",
								"click-type": "clicked",
								"object-clicked": "Character"
							}
						}
					],
					"actions": [
						{
							"id": "add-to-eventvar",
							"objectClass": "System",
							"sid": 463445977228586,
							"parameters": {
								"variable": "Currency",
								"value": "Character.ActiveTapCount"
							}
						},
						{
							"id": "play",
							"objectClass": "Audio",
							"sid": 973159661518707,
							"parameters": {
								"audio-file": "button_pop2",
								"loop": "not-looping",
								"volume": "0",
								"stereo-pan": "0",
								"tag-optional": "\"pop\""
							}
						}
					],
					"sid": 185690577727071
				},
				{
					"eventType": "block",
					"conditions": [
						{
							"id": "every-tick",
							"objectClass": "System",
							"sid": 343099920306374
						}
					],
					"actions": [
						{
							"id": "add-to-eventvar",
							"objectClass": "System",
							"sid": 411041352269730,
							"parameters": {
								"variable": "Currency",
								"value": "Character.PassiveTapCount"
							}
						}
					],
					"sid": 416546348910977
				},
				{
					"eventType": "block",
					"conditions": [
						{
							"id": "compare-two-values",
							"objectClass": "System",
							"sid": 849571510457814,
							"parameters": {
								"first-value": "Currency",
								"comparison": 5,
								"second-value": "0"
							}
						}
					],
					"actions": [
						{
							"id": "set-text",
							"objectClass": "CurrencyDisplay",
							"sid": 663996901433333,
							"parameters": {
								"text": "\"Coins: \" &Currency"
							}
						}
					],
					"sid": 811922587957739
				}
			],
			"sid": 622163293841462
		},
		{
			"eventType": "group",
			"disabled": false,
			"title": "CharacterStuff",
			"description": "",
			"isActiveOnStart": true,
			"children": [
				{
					"eventType": "variable",
					"name": "NivelTemp",
					"type": "number",
					"initialValue": "0",
					"comment": "",
					"isStatic": false,
					"isConstant": false,
					"sid": 626034729140917
				},
				{
					"functionName": "GetLvlFromClicks",
					"functionDescription": "",
					"functionCategory": "",
					"functionReturnType": "none",
					"functionCopyPicked": false,
					"functionIsAsync": false,
					"functionParameters": [
						{
							"name": "Clicks",
							"type": "number",
							"initialValue": "0",
							"comment": "",
							"sid": 826826210871674
						},
						{
							"name": "Nivel",
							"type": "number",
							"initialValue": "0",
							"comment": "",
							"sid": 395568928094520
						}
					],
					"eventType": "function-block",
					"conditions": [],
					"actions": [],
					"sid": 200532988401293,
					"children": [
						{
							"eventType": "block",
							"conditions": [
								{
									"id": "repeat",
									"objectClass": "System",
									"sid": 944937992829643,
									"parameters": {
										"count": "NivelArray.Width"
									}
								},
								{
									"id": "compare-two-values",
									"objectClass": "System",
									"sid": 788462189708799,
									"parameters": {
										"first-value": "NivelArray.At(loopindex)",
										"comparison": 3,
										"second-value": "Clicks"
									}
								}
							],
							"actions": [
								{
									"id": "set-eventvar-value",
									"objectClass": "System",
									"sid": 626030391691972,
									"parameters": {
										"variable": "NivelTemp",
										"value": "loopindex"
									}
								}
							],
							"sid": 933941744658892,
							"children": [
								{
									"eventType": "block",
									"conditions": [
										{
											"id": "compare-two-values",
											"objectClass": "System",
											"sid": 275460515739973,
											"parameters": {
												"first-value": "NivelArray.At(loopindex)",
												"comparison": 3,
												"second-value": "Clicks"
											}
										}
									],
									"actions": [
										{
											"id": "set-eventvar-value",
											"objectClass": "System",
											"sid": 829038039143312,
											"parameters": {
												"variable": "Nivel",
												"value": "loopindex"
											}
										}
									],
									"sid": 196303319969623
								}
							]
						},
						{
							"eventType": "block",
							"conditions": [
								{
									"id": "compare-two-values",
									"objectClass": "System",
									"sid": 340694444293880,
									"parameters": {
										"first-value": "NivelTemp",
										"comparison": 4,
										"second-value": "10"
									}
								}
							],
							"actions": [
								{
									"id": "set-eventvar-value",
									"objectClass": "System",
									"sid": 384316570194771,
									"parameters": {
										"variable": "NivelTemp",
										"value": "10220*(2^NivelTemp-10)"
									}
								}
							],
							"sid": 638258016804340
						}
					]
				},
				{
					"eventType": "block",
					"conditions": [
						{
							"id": "every-tick",
							"objectClass": "System",
							"sid": 827413238144396
						}
					],
					"actions": [
						{
							"callFunction": "GetLvlFromClicks",
							"sid": 413313353782100,
							"parameters": [
								"Currency",
								"0"
							]
						},
						{
							"id": "set-text",
							"objectClass": "LunaLevel",
							"sid": 473560500868696,
							"parameters": {
								"text": "\"Level: \" &NivelTemp"
							}
						}
					],
					"sid": 473504922336699
				}
			],
			"sid": 276675473409562
		},
		{
			"eventType": "group",
			"disabled": false,
			"title": "Shop",
			"description": "",
			"isActiveOnStart": true,
			"children": [
				{
					"eventType": "block",
					"conditions": [
						{
							"id": "on-object-clicked",
							"objectClass": "Mouse",
							"sid": 438912725707813,
							"parameters": {
								"mouse-button": "left",
								"click-type": "clicked",
								"object-clicked": "Col_bottle"
							}
						},
						{
							"id": "compare-instance-variable",
							"objectClass": "Col_bottle",
							"sid": 105711201230973,
							"parameters": {
								"instance-variable": "Bottle_lvl",
								"comparison": 3,
								"value": "10"
							}
						},
						{
							"id": "compare-eventvar",
							"objectClass": "System",
							"sid": 613262489319288,
							"parameters": {
								"variable": "Currency",
								"comparison": 5,
								"value": "Col_bottle.Price"
							}
						}
					],
					"actions": [
						{
							"id": "subtract-from-eventvar",
							"objectClass": "System",
							"sid": 467563397545901,
							"parameters": {
								"variable": "Currency",
								"value": "Col_bottle.Price"
							}
						},
						{
							"id": "add-to-instvar",
							"objectClass": "Col_bottle",
							"sid": 742954847750431,
							"parameters": {
								"instance-variable": "Bottle_lvl",
								"value": "1"
							}
						},
						{
							"id": "set-instvar-value",
							"objectClass": "Character",
							"sid": 966841515304791,
							"parameters": {
								"instance-variable": "PassiveTapCount",
								"value": "Character.PassiveTapCount*1.15^Col_bottle.Bottle_lvl"
							}
						},
						{
							"id": "set-instvar-value",
							"objectClass": "Col_bottle",
							"sid": 993309888065720,
							"parameters": {
								"instance-variable": "Price",
								"value": "Col_bottle.BasePrice*1.15^Col_bottle.Bottle_lvl"
							}
						},
						{
							"id": "spawn-another-object",
							"objectClass": "Col_bottle",
							"sid": 981959189438802,
							"parameters": {
								"object": "Text_Bottle",
								"layer": "0",
								"image-point": "1",
								"create-hierarchy": false,
								"template-name": "\"\""
							}
						},
						{
							"id": "set-text",
							"objectClass": "Text_Bottle",
							"sid": 756811041192058,
							"parameters": {
								"text": "Col_bottle.Price"
							}
						},
						{
							"id": "play",
							"objectClass": "Audio",
							"sid": 715856436099248,
							"parameters": {
								"audio-file": "collectible_v2",
								"loop": "not-looping",
								"volume": "0",
								"stereo-pan": "0",
								"tag-optional": "\"\""
							}
						}
					],
					"sid": 991089578848941
				},
				{
					"eventType": "block",
					"conditions": [
						{
							"id": "on-object-clicked",
							"objectClass": "Mouse",
							"sid": 854784110226173,
							"parameters": {
								"mouse-button": "left",
								"click-type": "clicked",
								"object-clicked": "Col_butterfly"
							}
						},
						{
							"id": "compare-instance-variable",
							"objectClass": "Col_butterfly",
							"sid": 999868643529920,
							"parameters": {
								"instance-variable": "Butterfly_lvl",
								"comparison": 3,
								"value": "10"
							}
						},
						{
							"id": "compare-eventvar",
							"objectClass": "System",
							"sid": 922079839321910,
							"parameters": {
								"variable": "Currency",
								"comparison": 5,
								"value": "Col_butterfly.Price"
							}
						}
					],
					"actions": [
						{
							"id": "subtract-from-eventvar",
							"objectClass": "System",
							"sid": 430409173388065,
							"parameters": {
								"variable": "Currency",
								"value": "Col_butterfly.Price"
							}
						},
						{
							"id": "set-eventvar-value",
							"objectClass": "System",
							"sid": 247486345957282,
							"parameters": {
								"variable": "Multiplier",
								"value": "Multiplier+Col_butterfly.Butterfly_lvl"
							}
						},
						{
							"id": "add-to-instvar",
							"objectClass": "Col_butterfly",
							"sid": 345001632426085,
							"parameters": {
								"instance-variable": "Butterfly_lvl",
								"value": "1"
							}
						},
						{
							"id": "set-instvar-value",
							"objectClass": "Col_butterfly",
							"sid": 568490535673280,
							"parameters": {
								"instance-variable": "Price",
								"value": "Col_butterfly.BasePrice*1.15^Col_butterfly.Butterfly_lvl"
							}
						},
						{
							"id": "spawn-another-object",
							"objectClass": "Col_butterfly",
							"sid": 148888548173100,
							"parameters": {
								"object": "Text_Butterly",
								"layer": "0",
								"image-point": "1",
								"create-hierarchy": false,
								"template-name": "\"\""
							}
						},
						{
							"id": "set-text",
							"objectClass": "Text_Butterly",
							"sid": 656839279068213,
							"parameters": {
								"text": "Col_butterfly.Price"
							}
						},
						{
							"id": "play",
							"objectClass": "Audio",
							"sid": 465008427996107,
							"parameters": {
								"audio-file": "collectible_v2",
								"loop": "not-looping",
								"volume": "0",
								"stereo-pan": "0",
								"tag-optional": "\"\""
							}
						}
					],
					"sid": 880618780593704
				},
				{
					"eventType": "block",
					"conditions": [
						{
							"id": "on-object-clicked",
							"objectClass": "Mouse",
							"sid": 367930828363129,
							"parameters": {
								"mouse-button": "left",
								"click-type": "clicked",
								"object-clicked": "Col_feather"
							}
						},
						{
							"id": "compare-eventvar",
							"objectClass": "System",
							"sid": 198536751582907,
							"parameters": {
								"variable": "Currency",
								"comparison": 5,
								"value": "Col_feather.Price"
							}
						}
					],
					"actions": [
						{
							"id": "subtract-from-eventvar",
							"objectClass": "System",
							"sid": 199638872654890,
							"parameters": {
								"variable": "Currency",
								"value": "Col_feather.Price"
							}
						},
						{
							"id": "set-eventvar-value",
							"objectClass": "System",
							"sid": 545325337478998,
							"disabled": true,
							"parameters": {
								"variable": "TapNumber",
								"value": "10"
							}
						},
						{
							"id": "set-instvar-value",
							"objectClass": "Col_feather",
							"sid": 159326537683103,
							"parameters": {
								"instance-variable": "Feather_lvl",
								"value": "Col_feather.BasePrice*1.15^Col_feather.Feather_lvl"
							}
						},
						{
							"id": "add-to-instvar",
							"objectClass": "Col_feather",
							"sid": 113394007504113,
							"parameters": {
								"instance-variable": "Feather_lvl",
								"value": "1"
							}
						},
						{
							"id": "spawn-another-object",
							"objectClass": "Col_feather",
							"sid": 594110657339653,
							"parameters": {
								"object": "Text_Feather",
								"layer": "0",
								"image-point": "1",
								"create-hierarchy": false,
								"template-name": "\"\""
							}
						},
						{
							"id": "set-text",
							"objectClass": "Text_Feather",
							"sid": 873709895818784,
							"parameters": {
								"text": "Col_feather.Price"
							}
						},
						{
							"id": "play",
							"objectClass": "Audio",
							"sid": 324806245777982,
							"parameters": {
								"audio-file": "collectible_v2",
								"loop": "not-looping",
								"volume": "0",
								"stereo-pan": "0",
								"tag-optional": "\"\""
							}
						}
					],
					"sid": 403279870010161
				},
				{
					"eventType": "block",
					"conditions": [
						{
							"id": "on-object-clicked",
							"objectClass": "Mouse",
							"sid": 599863006438663,
							"parameters": {
								"mouse-button": "left",
								"click-type": "clicked",
								"object-clicked": "Col_sword"
							}
						},
						{
							"id": "compare-eventvar",
							"objectClass": "System",
							"sid": 554284927886249,
							"parameters": {
								"variable": "Currency",
								"comparison": 5,
								"value": "Col_sword.Price"
							}
						}
					],
					"actions": [
						{
							"id": "subtract-from-eventvar",
							"objectClass": "System",
							"sid": 792656662189173,
							"parameters": {
								"variable": "Currency",
								"value": "Col_sword.Price"
							}
						},
						{
							"id": "set-eventvar-value",
							"objectClass": "System",
							"sid": 793383728157517,
							"disabled": true,
							"parameters": {
								"variable": "Multiplier",
								"value": "10"
							}
						},
						{
							"id": "set-instvar-value",
							"objectClass": "Col_sword",
							"sid": 143062364471434,
							"parameters": {
								"instance-variable": "Price",
								"value": "Col_sword.BasePrice*1.15^Col_sword.Sword_lvl"
							}
						},
						{
							"id": "add-to-instvar",
							"objectClass": "Col_sword",
							"sid": 853429794403744,
							"parameters": {
								"instance-variable": "Sword_lvl",
								"value": "1"
							}
						},
						{
							"id": "spawn-another-object",
							"objectClass": "Col_sword",
							"sid": 413164505616917,
							"parameters": {
								"object": "Text_Sword",
								"layer": "0",
								"image-point": "1",
								"create-hierarchy": false,
								"template-name": "\"\""
							}
						},
						{
							"id": "set-text",
							"objectClass": "Text_Sword",
							"sid": 948917574774291,
							"parameters": {
								"text": "Col_sword.Price"
							}
						},
						{
							"id": "play",
							"objectClass": "Audio",
							"sid": 371652146683614,
							"parameters": {
								"audio-file": "collectible_v2",
								"loop": "not-looping",
								"volume": "0",
								"stereo-pan": "0",
								"tag-optional": "\"\""
							}
						}
					],
					"sid": 323899632086318
				}
			],
			"sid": 889083086395243
		},
		{
			"eventType": "group",
			"disabled": false,
			"title": "Visual",
			"description": "",
			"isActiveOnStart": true,
			"children": [
				{
					"eventType": "group",
					"disabled": false,
					"title": "Squash",
					"description": "",
					"isActiveOnStart": true,
					"children": [
						{
							"eventType": "block",
							"conditions": [
								{
									"id": "on-object-clicked",
									"objectClass": "Mouse",
									"sid": 191844863697272,
									"parameters": {
										"mouse-button": "left",
										"click-type": "clicked",
										"object-clicked": "Character"
									}
								}
							],
							"actions": [
								{
									"id": "tween-two-properties",
									"objectClass": "Character",
									"sid": 916716063555180,
									"behaviorType": "Tween",
									"parameters": {
										"tags": "\"restore\"",
										"property": "size",
										"end-x": "OriginalHeight*0.95",
										"end-y": "OriginalWidth*1.05",
										"time": "0.05",
										"ease": "default",
										"destroy-on-complete": "no",
										"loop": "no",
										"ping-pong": "yes",
										"repeat-count": "1"
									}
								},
								{
									"id": "wait",
									"objectClass": "System",
									"sid": 653288885522162,
									"parameters": {
										"seconds": "0.1",
										"use-timescale": true
									}
								},
								{
									"id": "tween-two-properties",
									"objectClass": "Character",
									"sid": 830241902281247,
									"behaviorType": "Tween",
									"parameters": {
										"tags": "\"Squash\"",
										"property": "size",
										"end-x": "OriginalWidth",
										"end-y": "OriginalHeight",
										"time": "0.1",
										"ease": "default",
										"destroy-on-complete": "no",
										"loop": "no",
										"ping-pong": "yes",
										"repeat-count": "1"
									}
								}
							],
							"sid": 453903124821342,
							"children": [
								{
									"eventType": "block",
									"conditions": [
										{
											"id": "compare-two-values",
											"objectClass": "System",
											"sid": 797343518161644,
											"parameters": {
												"first-value": "Currency%2 ",
												"comparison": 0,
												"second-value": "0"
											}
										}
									],
									"actions": [
										{
											"id": "spawn-another-object",
											"objectClass": "Character",
											"sid": 270455507697213,
											"parameters": {
												"object": "Parts_Star2",
												"layer": "1",
												"image-point": "2",
												"create-hierarchy": false,
												"template-name": "\"\""
											}
										},
										{
											"id": "set-spray-cone",
											"objectClass": "Parts_Star2",
											"sid": 766013119246084,
											"parameters": {
												"spray-cone": "360"
											}
										},
										{
											"id": "set-initial-speed-randomiser",
											"objectClass": "Parts_Star2",
											"sid": 187805697378170,
											"parameters": {
												"speed-randomiser": "50"
											}
										}
									],
									"sid": 873122176962045
								},
								{
									"eventType": "block",
									"conditions": [
										{
											"id": "compare-two-values",
											"objectClass": "System",
											"sid": 503169231522204,
											"parameters": {
												"first-value": "Currency%2",
												"comparison": 1,
												"second-value": "0"
											}
										}
									],
									"actions": [
										{
											"id": "spawn-another-object",
											"objectClass": "Character",
											"sid": 357066150791852,
											"parameters": {
												"object": "Part_Star1",
												"layer": "1",
												"image-point": "2",
												"create-hierarchy": false,
												"template-name": "\"\""
											}
										},
										{
											"id": "set-spray-cone",
											"objectClass": "Part_Star1",
											"sid": 814214693524300,
											"parameters": {
												"spray-cone": "360"
											}
										},
										{
											"id": "set-initial-speed-randomiser",
											"objectClass": "Part_Star1",
											"sid": 776887347728610,
											"parameters": {
												"speed-randomiser": "50"
											}
										}
									],
									"sid": 578931916916404
								}
							]
						}
					],
					"sid": 684369212890450
				},
				{
					"eventType": "block",
					"conditions": [
						{
							"id": "compare-eventvar",
							"objectClass": "System",
							"sid": 695487300514759,
							"parameters": {
								"variable": "Currency",
								"comparison": 5,
								"value": "Col_bottle.Price"
							}
						}
					],
					"actions": [],
					"sid": 975450734662202
				},
				{
					"eventType": "block",
					"conditions": [
						{
							"id": "compare-eventvar",
							"objectClass": "System",
							"sid": 973823117273707,
							"parameters": {
								"variable": "Currency",
								"comparison": 5,
								"value": "Col_butterfly.Price"
							}
						}
					],
					"actions": [
						{
							"id": "spawn-another-object",
							"objectClass": "Col_butterfly",
							"sid": 126131008405887,
							"parameters": {
								"object": "Glow_butterfly",
								"layer": "0",
								"image-point": "0",
								"create-hierarchy": false,
								"template-name": "\"\""
							}
						}
					],
					"sid": 174930639789035
				}
			],
			"sid": 655019594919060
		}
	],
	"sid": 672777573896994
}